<?xml version="1.0" encoding="utf-8"?>
<!--DO NOT EDIT. This document is generated by PSoC Creator design builds.-->
<PSoCCreatorIdeExport Version="1">
  <Device Part="CY8C4247LQI-BL483" Processor="CortexM0" DeviceID="E34119E" />
  <Toolchains>
    <Toolchain Name="ARM GCC Generic" Selected="True">
      <Tool Name="prebuild" Command="" Options="" />
      <Tool Name="assembler" Command="arm-none-eabi-as.exe" Options="-mcpu=cortex-m0 -mthumb -I. -IGenerated_Source\PSoC4 -alh=${OutputDir}/${CompileFile}.lst -g -W" />
      <Tool Name="compiler" Command="arm-none-eabi-gcc.exe" Options="-mcpu=cortex-m0 -mthumb -I. -IGenerated_Source\PSoC4 -Wa,-alh=${OutputDir}/${CompileFile}.lst -g -D DEBUG -Wall -ffunction-sections -Og -ffat-lto-objects" />
      <Tool Name="linker" Command="arm-none-eabi-gcc.exe" Options="-mcpu=cortex-m0 -mthumb -g -ffunction-sections -Og -ffat-lto-objects -L Generated_Source\PSoC4 -L .\LinkerScripts -Wl,-Map,${OutputDir}/${ProjectShortName}.map -T .\LinkerScripts\cm0gcc.ld -specs=nano.specs -Wl,--gc-sections" />
      <Tool Name="postbuild" Command="" Options="" />
    </Toolchain>
    <Toolchain Name="ARM MDK Generic" Selected="False">
      <Tool Name="prebuild" Command="" Options="" />
      <Tool Name="assembler" Command="armasm.exe" Options="--cpu=Cortex-M0 --diag_style=gnu --thumb -i. -iGenerated_Source\PSoC4 -g --list=${OutputDir}/${CompileFile}.lst" />
      <Tool Name="compiler" Command="armcc.exe" Options="--cpu=Cortex-M0 --diag_style=gnu -I. -IGenerated_Source\PSoC4 --list --signed_chars -g -D DEBUG -O0 --split_sections" />
      <Tool Name="linker" Command="armlink.exe" Options="--cpu=Cortex-M0 --diag_style=gnu --no_startup --library_type=microlib --map --list ${OutputDir}/${ProjectShortName}.map --scatter &quot;C:\Users\Nick\Documents\PSoC Creator\capsenseled1\capsenseled\capsenseled.cydsn\Generated_Source\PSoC4\Cm0RealView.scat&quot;" />
      <Tool Name="postbuild" Command="" Options="" />
    </Toolchain>
    <Toolchain Name="ARM IAR Generic" Selected="False">
      <Tool Name="prebuild" Command="" Options="" />
      <Tool Name="assembler" Command="iasmarm.exe" Options="--cpu Cortex-M0 -I. -IGenerated_Source\PSoC4 -s+ -M&lt;&gt; -w+ -r -DDEBUG --fpu None" />
      <Tool Name="compiler" Command="iccarm.exe" Options="--cpu Cortex-M0 -I. -IGenerated_Source\PSoC4 -D DEBUG --no_cse --no_unroll --no_inline --no_code_motion --no_tbaa --no_clustering --no_scheduling --debug --endian=little -e --fpu=None -On --no_wrap_diagnostics" />
      <Tool Name="linker" Command="ilinkarm.exe" Options="--semihosting --entry __iar_program_start --config Generated_Source\PSoC4\Generated_Source\PSoC4\Cm0Iar.icf" />
      <Tool Name="postbuild" Command="" Options="" />
    </Toolchain>
  </Toolchains>
  <Project Name="capsenseled" Path="C:\Users\Nick\Documents\PSoC Creator\capsenseled1\capsenseled\capsenseled.cydsn" Version="5.20" Type="Bootloadable">
    <CMSIS_SVD_File>capsenseled.svd</CMSIS_SVD_File>
    <Datasheet />
    <LinkerFiles>
      <LinkerFile Toolchain="ARM GCC Generic">.\LinkerScripts\cm0gcc.ld</LinkerFile>
      <LinkerFile Toolchain="ARM MDK Generic">.\Generated_Source\PSoC4\Cm0RealView.scat</LinkerFile>
      <LinkerFile Toolchain="ARM IAR Generic">.\Generated_Source\PSoC4\Cm0Iar.icf</LinkerFile>
    </LinkerFiles>
    <Folders>
      <Folder BuildType="STRICT" Path="C:\Users\Nick\Documents\PSoC Creator\capsenseled1\capsenseled\capsenseled.cydsn">
        <Files Root="C:\Users\Nick\Documents\PSoC Creator\capsenseled1\capsenseled\capsenseled.cydsn">
          <File BuildType="BUILD" Toolchain="">main.c</File>
          <File BuildType="BUILD" Toolchain="">debug.c</File>
          <File BuildType="BUILD" Toolchain="">OTAMandatory.c</File>
          <File BuildType="BUILD" Toolchain="">OTAOptional.c</File>
          <File BuildType="BUILD" Toolchain="">adc.c</File>
          <File BuildType="BUILD" Toolchain="">filter.c</File>
          <File BuildType="BUILD" Toolchain="">IDAC.c</File>
          <File BuildType="BUILD" Toolchain="">PGA.c</File>
          <File BuildType="BUILD" Toolchain="">queue.c</File>
          <File BuildType="BUILD" Toolchain="">PWM.c</File>
          <File BuildType="BUILD" Toolchain="">fsm.c</File>
          <File BuildType="BUILD" Toolchain="">BLE.c</File>
          <File BuildType="BUILD" Toolchain="">print.c</File>
          <File BuildType="BUILD" Toolchain="">CyBLE_custom.h</File>
          <File BuildType="BUILD" Toolchain="">Options.h</File>
          <File BuildType="BUILD" Toolchain="">OTAMandatory.h</File>
          <File BuildType="BUILD" Toolchain="">OTAOptional.h</File>
          <File BuildType="BUILD" Toolchain="">common.h</File>
          <File BuildType="BUILD" Toolchain="">Debug.h</File>
          <File BuildType="BUILD" Toolchain="">main.h</File>
          <File BuildType="BUILD" Toolchain="">adc.h</File>
          <File BuildType="BUILD" Toolchain="">cyapicallbacks.h</File>
          <File BuildType="BUILD" Toolchain="">filter.h</File>
          <File BuildType="BUILD" Toolchain="">IDAC.h</File>
          <File BuildType="BUILD" Toolchain="">PGA.h</File>
          <File BuildType="BUILD" Toolchain="">PWM.h</File>
          <File BuildType="BUILD" Toolchain="">queue.h</File>
          <File BuildType="BUILD" Toolchain="">user_cfg_def.h</File>
          <File BuildType="BUILD" Toolchain="">BLE.h</File>
          <File BuildType="BUILD" Toolchain="">fsm.h</File>
          <File BuildType="BUILD" Toolchain="">print.h</File>
        </Files>
      </Folder>
      <Folder BuildType="STRICT" Path="C:\Users\Nick\Documents\PSoC Creator\capsenseled1\capsenseled\capsenseled.cydsn\Generated_Source\PSoC4">
        <Files Root="C:\Users\Nick\Documents\PSoC Creator\capsenseled1\capsenseled\capsenseled.cydsn">
          <File BuildType="BUILD" Toolchain="">Generated_Source\PSoC4\cyfitter_cfg.h</File>
          <File BuildType="BUILD" Toolchain="">Generated_Source\PSoC4\cyfitter_cfg.c</File>
          <File BuildType="BUILD" Toolchain="">Generated_Source\PSoC4\cymetadata.c</File>
          <File BuildType="BUILD" Toolchain="">Generated_Source\PSoC4\cydevice_trm.h</File>
          <File BuildType="BUILD" Toolchain="">Generated_Source\PSoC4\cydevicegnu_trm.inc</File>
          <File BuildType="BUILD" Toolchain="">Generated_Source\PSoC4\cydevicerv_trm.inc</File>
          <File BuildType="BUILD" Toolchain="">Generated_Source\PSoC4\cydeviceiar_trm.inc</File>
          <File BuildType="BUILD" Toolchain="">Generated_Source\PSoC4\cyfittergnu.inc</File>
          <File BuildType="BUILD" Toolchain="">Generated_Source\PSoC4\cyfitterrv.inc</File>
          <File BuildType="BUILD" Toolchain="">Generated_Source\PSoC4\cyfitteriar.inc</File>
          <File BuildType="BUILD" Toolchain="">Generated_Source\PSoC4\cyfitter.h</File>
          <File BuildType="BUILD" Toolchain="">Generated_Source\PSoC4\cydisabledsheets.h</File>
          <File BuildType="BUILD" Toolchain="">Generated_Source\PSoC4\Clock_1.c</File>
          <File BuildType="BUILD" Toolchain="">Generated_Source\PSoC4\Clock_1.h</File>
          <File BuildType="BUILD" Toolchain="">Generated_Source\PSoC4\cycodeshareimport.ld</File>
          <File BuildType="BUILD" Toolchain="">Generated_Source\PSoC4\cycodeshareexport.ld</File>
          <File BuildType="BUILD" Toolchain="">Generated_Source\PSoC4\cycodeshareimport.scat</File>
          <File BuildType="BUILD" Toolchain="ARM GCC Generic">Generated_Source\PSoC4\cm0gcc.ld</File>
          <File BuildType="BUILD" Toolchain="ARM MDK Generic">Generated_Source\PSoC4\Cm0RealView.scat</File>
          <File BuildType="BUILD" Toolchain="">Generated_Source\PSoC4\Cm0Start.c</File>
          <File BuildType="BUILD" Toolchain="">Generated_Source\PSoC4\core_cm0_psoc4.h</File>
          <File BuildType="BUILD" Toolchain="">Generated_Source\PSoC4\core_cm0.h</File>
          <File BuildType="BUILD" Toolchain="ARM GCC Generic">Generated_Source\PSoC4\CyBootAsmGnu.s</File>
          <File BuildType="BUILD" Toolchain="ARM MDK Generic">Generated_Source\PSoC4\CyBootAsmRv.s</File>
          <File BuildType="BUILD" Toolchain="">Generated_Source\PSoC4\CyFlash.c</File>
          <File BuildType="BUILD" Toolchain="">Generated_Source\PSoC4\CyFlash.h</File>
          <File BuildType="BUILD" Toolchain="">Generated_Source\PSoC4\CyLib.c</File>
          <File BuildType="BUILD" Toolchain="">Generated_Source\PSoC4\CyLib.h</File>
          <File BuildType="BUILD" Toolchain="">Generated_Source\PSoC4\cyPm.c</File>
          <File BuildType="BUILD" Toolchain="">Generated_Source\PSoC4\cyPm.h</File>
          <File BuildType="BUILD" Toolchain="">Generated_Source\PSoC4\cytypes.h</File>
          <File BuildType="BUILD" Toolchain="">Generated_Source\PSoC4\cyutils.c</File>
          <File BuildType="BUILD" Toolchain="">Generated_Source\PSoC4\cypins.h</File>
          <File BuildType="BUILD" Toolchain="">Generated_Source\PSoC4\core_cmFunc.h</File>
          <File BuildType="BUILD" Toolchain="">Generated_Source\PSoC4\core_cmInstr.h</File>
          <File BuildType="BUILD" Toolchain="ARM IAR Generic">Generated_Source\PSoC4\Cm0Iar.icf</File>
          <File BuildType="BUILD" Toolchain="ARM IAR Generic">Generated_Source\PSoC4\CyBootAsmIar.s</File>
          <File BuildType="BUILD" Toolchain="">Generated_Source\PSoC4\CyLFClk.c</File>
          <File BuildType="BUILD" Toolchain="">Generated_Source\PSoC4\CyLFClk.h</File>
          <File BuildType="BUILD" Toolchain="">Generated_Source\PSoC4\project.h</File>
          <File BuildType="BUILD" Toolchain="">Generated_Source\PSoC4\UART.c</File>
          <File BuildType="BUILD" Toolchain="">Generated_Source\PSoC4\UART.h</File>
          <File BuildType="BUILD" Toolchain="">Generated_Source\PSoC4\UART_PVT.h</File>
          <File BuildType="BUILD" Toolchain="ARM GCC Generic">Generated_Source\PSoC4\UART_AsmGnu.s</File>
          <File BuildType="BUILD" Toolchain="ARM MDK Generic">Generated_Source\PSoC4\UART_AsmRv.s</File>
          <File BuildType="BUILD" Toolchain="ARM IAR Generic">Generated_Source\PSoC4\UART_AsmIar.s</File>
          <File BuildType="BUILD" Toolchain="">Generated_Source\PSoC4\cybootloader.icf</File>
          <File BuildType="BUILD" Toolchain="">Generated_Source\PSoC4\cybootloader.c</File>
          <File BuildType="BUILD" Toolchain="">Generated_Source\PSoC4\WDT_Interrupt.c</File>
          <File BuildType="BUILD" Toolchain="">Generated_Source\PSoC4\WDT_Interrupt.h</File>
          <File BuildType="BUILD" Toolchain="">Generated_Source\PSoC4\Bootloadable.c</File>
          <File BuildType="BUILD" Toolchain="">Generated_Source\PSoC4\Bootloadable.h</File>
          <File BuildType="BUILD" Toolchain="">Generated_Source\PSoC4\Mid_Thresh.c</File>
          <File BuildType="BUILD" Toolchain="">Generated_Source\PSoC4\Mid_Thresh.h</File>
          <File BuildType="BUILD" Toolchain="">Generated_Source\PSoC4\Mid_Thresh_aliases.h</File>
          <File BuildType="BUILD" Toolchain="">Generated_Source\PSoC4\Mid_Thresh_PM.c</File>
          <File BuildType="BUILD" Toolchain="">Generated_Source\PSoC4\PWM_High_Thresh.c</File>
          <File BuildType="BUILD" Toolchain="">Generated_Source\PSoC4\PWM_High_Thresh.h</File>
          <File BuildType="BUILD" Toolchain="">Generated_Source\PSoC4\PWM_High_Thresh_PM.c</File>
          <File BuildType="BUILD" Toolchain="">Generated_Source\PSoC4\Low_Thresh.c</File>
          <File BuildType="BUILD" Toolchain="">Generated_Source\PSoC4\Low_Thresh.h</File>
          <File BuildType="BUILD" Toolchain="">Generated_Source\PSoC4\Low_Thresh_aliases.h</File>
          <File BuildType="BUILD" Toolchain="">Generated_Source\PSoC4\Low_Thresh_PM.c</File>
          <File BuildType="BUILD" Toolchain="">Generated_Source\PSoC4\PWM_Mid_Thresh.c</File>
          <File BuildType="BUILD" Toolchain="">Generated_Source\PSoC4\PWM_Mid_Thresh.h</File>
          <File BuildType="BUILD" Toolchain="">Generated_Source\PSoC4\PWM_Mid_Thresh_PM.c</File>
          <File BuildType="BUILD" Toolchain="">Generated_Source\PSoC4\PWM_Low_Thresh.c</File>
          <File BuildType="BUILD" Toolchain="">Generated_Source\PSoC4\PWM_Low_Thresh.h</File>
          <File BuildType="BUILD" Toolchain="">Generated_Source\PSoC4\PWM_Low_Thresh_PM.c</File>
          <File BuildType="BUILD" Toolchain="">Generated_Source\PSoC4\TC_CC_ISR.c</File>
          <File BuildType="BUILD" Toolchain="">Generated_Source\PSoC4\TC_CC_ISR.h</File>
          <File BuildType="BUILD" Toolchain="">Generated_Source\PSoC4\Timer.c</File>
          <File BuildType="BUILD" Toolchain="">Generated_Source\PSoC4\Timer.h</File>
          <File BuildType="BUILD" Toolchain="">Generated_Source\PSoC4\Timer_PM.c</File>
          <File BuildType="BUILD" Toolchain="">Generated_Source\PSoC4\High_Thresh.c</File>
          <File BuildType="BUILD" Toolchain="">Generated_Source\PSoC4\High_Thresh.h</File>
          <File BuildType="BUILD" Toolchain="">Generated_Source\PSoC4\High_Thresh_aliases.h</File>
          <File BuildType="BUILD" Toolchain="">Generated_Source\PSoC4\High_Thresh_PM.c</File>
          <File BuildType="BUILD" Toolchain="">Generated_Source\PSoC4\LED_GREEN.c</File>
          <File BuildType="BUILD" Toolchain="">Generated_Source\PSoC4\LED_GREEN.h</File>
          <File BuildType="BUILD" Toolchain="">Generated_Source\PSoC4\LED_GREEN_aliases.h</File>
          <File BuildType="BUILD" Toolchain="">Generated_Source\PSoC4\LED_GREEN_PM.c</File>
          <File BuildType="BUILD" Toolchain="">Generated_Source\PSoC4\LED_BLUE.c</File>
          <File BuildType="BUILD" Toolchain="">Generated_Source\PSoC4\LED_BLUE.h</File>
          <File BuildType="BUILD" Toolchain="">Generated_Source\PSoC4\LED_BLUE_aliases.h</File>
          <File BuildType="BUILD" Toolchain="">Generated_Source\PSoC4\LED_BLUE_PM.c</File>
          <File BuildType="BUILD" Toolchain="">Generated_Source\PSoC4\LOW_FILTER_INPUT.c</File>
          <File BuildType="BUILD" Toolchain="">Generated_Source\PSoC4\LOW_FILTER_INPUT.h</File>
          <File BuildType="BUILD" Toolchain="">Generated_Source\PSoC4\LOW_FILTER_INPUT_aliases.h</File>
          <File BuildType="BUILD" Toolchain="">Generated_Source\PSoC4\LOW_FILTER_INPUT_PM.c</File>
          <File BuildType="BUILD" Toolchain="">Generated_Source\PSoC4\HIGH_FILTER_INPUT.c</File>
          <File BuildType="BUILD" Toolchain="">Generated_Source\PSoC4\HIGH_FILTER_INPUT.h</File>
          <File BuildType="BUILD" Toolchain="">Generated_Source\PSoC4\HIGH_FILTER_INPUT_aliases.h</File>
          <File BuildType="BUILD" Toolchain="">Generated_Source\PSoC4\HIGH_FILTER_INPUT_PM.c</File>
          <File BuildType="BUILD" Toolchain="">Generated_Source\PSoC4\LED_RED.c</File>
          <File BuildType="BUILD" Toolchain="">Generated_Source\PSoC4\LED_RED.h</File>
          <File BuildType="BUILD" Toolchain="">Generated_Source\PSoC4\LED_RED_aliases.h</File>
          <File BuildType="BUILD" Toolchain="">Generated_Source\PSoC4\LED_RED_PM.c</File>
          <File BuildType="BUILD" Toolchain="">Generated_Source\PSoC4\FIRE_FILTER_INPUT.c</File>
          <File BuildType="BUILD" Toolchain="">Generated_Source\PSoC4\FIRE_FILTER_INPUT.h</File>
          <File BuildType="BUILD" Toolchain="">Generated_Source\PSoC4\FIRE_FILTER_INPUT_aliases.h</File>
          <File BuildType="BUILD" Toolchain="">Generated_Source\PSoC4\FIRE_FILTER_INPUT_PM.c</File>
          <File BuildType="BUILD" Toolchain="">Generated_Source\PSoC4\IDAC_Fire_Thresh.c</File>
          <File BuildType="BUILD" Toolchain="">Generated_Source\PSoC4\IDAC_Fire_Thresh.h</File>
          <File BuildType="BUILD" Toolchain="">Generated_Source\PSoC4\IDAC_Fire_Thresh_PM.c</File>
          <File BuildType="BUILD" Toolchain="">Generated_Source\PSoC4\Fire_Thresh.c</File>
          <File BuildType="BUILD" Toolchain="">Generated_Source\PSoC4\Fire_Thresh.h</File>
          <File BuildType="BUILD" Toolchain="">Generated_Source\PSoC4\Fire_Thresh_aliases.h</File>
          <File BuildType="BUILD" Toolchain="">Generated_Source\PSoC4\Fire_Thresh_PM.c</File>
          <File BuildType="BUILD" Toolchain="">Generated_Source\PSoC4\ADC_SAR_Seq_1.c</File>
          <File BuildType="BUILD" Toolchain="">Generated_Source\PSoC4\ADC_SAR_Seq_1.h</File>
          <File BuildType="BUILD" Toolchain="">Generated_Source\PSoC4\ADC_SAR_Seq_1_PM.c</File>
          <File BuildType="BUILD" Toolchain="">Generated_Source\PSoC4\ADC_SAR_Seq_1_INT.c</File>
          <File BuildType="BUILD" Toolchain="">Generated_Source\PSoC4\Low_Thresh_Feedback.c</File>
          <File BuildType="BUILD" Toolchain="">Generated_Source\PSoC4\Low_Thresh_Feedback.h</File>
          <File BuildType="BUILD" Toolchain="">Generated_Source\PSoC4\Low_Thresh_Feedback_aliases.h</File>
          <File BuildType="BUILD" Toolchain="">Generated_Source\PSoC4\Low_Thresh_Feedback_PM.c</File>
          <File BuildType="BUILD" Toolchain="">Generated_Source\PSoC4\Mid_Thresh_Feedback.c</File>
          <File BuildType="BUILD" Toolchain="">Generated_Source\PSoC4\Mid_Thresh_Feedback.h</File>
          <File BuildType="BUILD" Toolchain="">Generated_Source\PSoC4\Mid_Thresh_Feedback_aliases.h</File>
          <File BuildType="BUILD" Toolchain="">Generated_Source\PSoC4\Mid_Thresh_Feedback_PM.c</File>
          <File BuildType="BUILD" Toolchain="">Generated_Source\PSoC4\High_Thresh_Feedback.c</File>
          <File BuildType="BUILD" Toolchain="">Generated_Source\PSoC4\High_Thresh_Feedback.h</File>
          <File BuildType="BUILD" Toolchain="">Generated_Source\PSoC4\High_Thresh_Feedback_aliases.h</File>
          <File BuildType="BUILD" Toolchain="">Generated_Source\PSoC4\High_Thresh_Feedback_PM.c</File>
          <File BuildType="BUILD" Toolchain="">Generated_Source\PSoC4\Fire_Thresh_Feedback.c</File>
          <File BuildType="BUILD" Toolchain="">Generated_Source\PSoC4\Fire_Thresh_Feedback.h</File>
          <File BuildType="BUILD" Toolchain="">Generated_Source\PSoC4\Fire_Thresh_Feedback_aliases.h</File>
          <File BuildType="BUILD" Toolchain="">Generated_Source\PSoC4\Fire_Thresh_Feedback_PM.c</File>
          <File BuildType="BUILD" Toolchain="">Generated_Source\PSoC4\motor.c</File>
          <File BuildType="BUILD" Toolchain="">Generated_Source\PSoC4\motor.h</File>
          <File BuildType="BUILD" Toolchain="">Generated_Source\PSoC4\motor_aliases.h</File>
          <File BuildType="BUILD" Toolchain="">Generated_Source\PSoC4\motor_PM.c</File>
          <File BuildType="BUILD" Toolchain="">Generated_Source\PSoC4\PGA_CS.c</File>
          <File BuildType="BUILD" Toolchain="">Generated_Source\PSoC4\PGA_CS.h</File>
          <File BuildType="BUILD" Toolchain="">Generated_Source\PSoC4\PGA_CS_aliases.h</File>
          <File BuildType="BUILD" Toolchain="">Generated_Source\PSoC4\PGA_CS_PM.c</File>
          <File BuildType="BUILD" Toolchain="">Generated_Source\PSoC4\PGA_U_Db.c</File>
          <File BuildType="BUILD" Toolchain="">Generated_Source\PSoC4\PGA_U_Db.h</File>
          <File BuildType="BUILD" Toolchain="">Generated_Source\PSoC4\PGA_U_Db_aliases.h</File>
          <File BuildType="BUILD" Toolchain="">Generated_Source\PSoC4\PGA_U_Db_PM.c</File>
          <File BuildType="BUILD" Toolchain="">Generated_Source\PSoC4\PGA_INC.c</File>
          <File BuildType="BUILD" Toolchain="">Generated_Source\PSoC4\PGA_INC.h</File>
          <File BuildType="BUILD" Toolchain="">Generated_Source\PSoC4\PGA_INC_aliases.h</File>
          <File BuildType="BUILD" Toolchain="">Generated_Source\PSoC4\PGA_INC_PM.c</File>
          <File BuildType="BUILD" Toolchain="">Generated_Source\PSoC4\Clock_PWM.c</File>
          <File BuildType="BUILD" Toolchain="">Generated_Source\PSoC4\Clock_PWM.h</File>
          <File BuildType="BUILD" Toolchain="">Generated_Source\PSoC4\ADC_SAR_Seq_1_IRQ.c</File>
          <File BuildType="BUILD" Toolchain="">Generated_Source\PSoC4\ADC_SAR_Seq_1_IRQ.h</File>
          <File BuildType="BUILD" Toolchain="">Generated_Source\PSoC4\ADC_SAR_Seq_1_intClock.c</File>
          <File BuildType="BUILD" Toolchain="">Generated_Source\PSoC4\ADC_SAR_Seq_1_intClock.h</File>
          <File BuildType="BUILD" Toolchain="">Generated_Source\PSoC4\Low_Peak.c</File>
          <File BuildType="BUILD" Toolchain="">Generated_Source\PSoC4\Low_Peak.h</File>
          <File BuildType="BUILD" Toolchain="">Generated_Source\PSoC4\Low_Peak_aliases.h</File>
          <File BuildType="BUILD" Toolchain="">Generated_Source\PSoC4\Low_Peak_PM.c</File>
          <File BuildType="BUILD" Toolchain="">Generated_Source\PSoC4\Mid_Peak.c</File>
          <File BuildType="BUILD" Toolchain="">Generated_Source\PSoC4\Mid_Peak.h</File>
          <File BuildType="BUILD" Toolchain="">Generated_Source\PSoC4\Mid_Peak_aliases.h</File>
          <File BuildType="BUILD" Toolchain="">Generated_Source\PSoC4\Mid_Peak_PM.c</File>
          <File BuildType="BUILD" Toolchain="">Generated_Source\PSoC4\High_Peak.c</File>
          <File BuildType="BUILD" Toolchain="">Generated_Source\PSoC4\High_Peak.h</File>
          <File BuildType="BUILD" Toolchain="">Generated_Source\PSoC4\High_Peak_aliases.h</File>
          <File BuildType="BUILD" Toolchain="">Generated_Source\PSoC4\High_Peak_PM.c</File>
          <File BuildType="BUILD" Toolchain="">Generated_Source\PSoC4\Fire_Peak.c</File>
          <File BuildType="BUILD" Toolchain="">Generated_Source\PSoC4\Fire_Peak.h</File>
          <File BuildType="BUILD" Toolchain="">Generated_Source\PSoC4\Fire_Peak_aliases.h</File>
          <File BuildType="BUILD" Toolchain="">Generated_Source\PSoC4\Fire_Peak_PM.c</File>
          <File BuildType="BUILD" Toolchain="">Generated_Source\PSoC4\MID_FILTER_INPUT.c</File>
          <File BuildType="BUILD" Toolchain="">Generated_Source\PSoC4\MID_FILTER_INPUT.h</File>
          <File BuildType="BUILD" Toolchain="">Generated_Source\PSoC4\MID_FILTER_INPUT_aliases.h</File>
          <File BuildType="BUILD" Toolchain="">Generated_Source\PSoC4\MID_FILTER_INPUT_PM.c</File>
        </Files>
      </Folder>
      <Folder BuildType="STRICT" Path="C:\Users\Nick\Documents\PSoC Creator\capsenseled1\capsenseled\capsenseled.cydsn\LinkerScripts">
        <Files Root="C:\Users\Nick\Documents\PSoC Creator\capsenseled1\capsenseled\capsenseled.cydsn">
          <File BuildType="BUILD" Toolchain="ARM GCC Generic">LinkerScripts\cm0gcc.ld</File>
          <File BuildType="BUILD" Toolchain="ARM IAR Generic">LinkerScripts\Cm0Iar.icf</File>
          <File BuildType="BUILD" Toolchain="ARM MDK Generic">LinkerScripts\Cm0Mdk.scat</File>
          <File BuildType="BUILD" Toolchain="ARM GCC Generic">LinkerScripts\BootloaderSymbolsGcc.ld</File>
        </Files>
      </Folder>
      <Folder BuildType="STRICT" Path="C:\Users\Nick\Documents\PSoC Creator\capsenseled1\capsenseled\capsenseled.cydsn\Export\ARM_GCC_Generic">
        <Files Root="C:\Users\Nick\Documents\PSoC Creator\capsenseled1\capsenseled\capsenseled.cydsn">
          <File BuildType="BUILD" Toolchain="ARM GCC Generic">.\Export\ARM_GCC_Generic\CyComponentLibrary.a</File>
        </Files>
      </Folder>
      <Folder BuildType="STRICT" Path="C:\Users\Nick\Documents\PSoC Creator\capsenseled1\capsenseled\capsenseled.cydsn\Export\ARM_MDK_Generic">
        <Files Root="C:\Users\Nick\Documents\PSoC Creator\capsenseled1\capsenseled\capsenseled.cydsn">
          <File BuildType="BUILD" Toolchain="ARM MDK Generic">.\Export\ARM_MDK_Generic\CyComponentLibrary.a</File>
        </Files>
      </Folder>
      <Folder BuildType="STRICT" Path="C:\Users\Nick\Documents\PSoC Creator\capsenseled1\capsenseled\capsenseled.cydsn\Export\ARM_IAR_Generic">
        <Files Root="C:\Users\Nick\Documents\PSoC Creator\capsenseled1\capsenseled\capsenseled.cydsn">
          <File BuildType="BUILD" Toolchain="ARM IAR Generic">.\Export\ARM_IAR_Generic\CyComponentLibrary.a</File>
        </Files>
      </Folder>
      <Folder BuildType="EXCLUDE" Path=".\codegentemp">
        <Files Root="C:\Users\Nick\Documents\PSoC Creator\capsenseled1\capsenseled\capsenseled.cydsn" />
      </Folder>
      <Folder BuildType="EXCLUDE" Path=".\ARM_GCC_441">
        <Files Root="C:\Users\Nick\Documents\PSoC Creator\capsenseled1\capsenseled\capsenseled.cydsn" />
      </Folder>
      <Folder BuildType="EXCLUDE" Path=".\ARM_GCC_473">
        <Files Root="C:\Users\Nick\Documents\PSoC Creator\capsenseled1\capsenseled\capsenseled.cydsn" />
      </Folder>
      <Folder BuildType="EXCLUDE" Path=".\DP8051_Keil_952">
        <Files Root="C:\Users\Nick\Documents\PSoC Creator\capsenseled1\capsenseled\capsenseled.cydsn" />
      </Folder>
      <Folder BuildType="EXCLUDE" Path=".\DP8051">
        <Files Root="C:\Users\Nick\Documents\PSoC Creator\capsenseled1\capsenseled\capsenseled.cydsn" />
      </Folder>
      <Folder BuildType="EXCLUDE" Path=".\CortexM0">
        <Files Root="C:\Users\Nick\Documents\PSoC Creator\capsenseled1\capsenseled\capsenseled.cydsn" />
      </Folder>
      <Folder BuildType="EXCLUDE" Path=".\CortexM0p">
        <Files Root="C:\Users\Nick\Documents\PSoC Creator\capsenseled1\capsenseled\capsenseled.cydsn" />
      </Folder>
      <Folder BuildType="EXCLUDE" Path=".\CortexM3">
        <Files Root="C:\Users\Nick\Documents\PSoC Creator\capsenseled1\capsenseled\capsenseled.cydsn" />
      </Folder>
      <Folder BuildType="EXCLUDE" Path=".\CortexM4">
        <Files Root="C:\Users\Nick\Documents\PSoC Creator\capsenseled1\capsenseled\capsenseled.cydsn" />
      </Folder>
      <Folder BuildType="EXCLUDE" Path=".\CortexM7">
        <Files Root="C:\Users\Nick\Documents\PSoC Creator\capsenseled1\capsenseled\capsenseled.cydsn" />
      </Folder>
      <Folder BuildType="EXCLUDE" Path=".\Generated_Source\PSoC3">
        <Files Root="C:\Users\Nick\Documents\PSoC Creator\capsenseled1\capsenseled\capsenseled.cydsn" />
      </Folder>
      <Folder BuildType="EXCLUDE" Path=".\Generated_Source\PSoC5">
        <Files Root="C:\Users\Nick\Documents\PSoC Creator\capsenseled1\capsenseled\capsenseled.cydsn" />
      </Folder>
    </Folders>
  </Project>
</PSoCCreatorIdeExport>